lsc/__init__.py
lsc/__main__.py
lsc/compileLogicScheme.py
lsc/core.py
lsc_mentalblood-1.1.dist-info/LICENSE
lsc_mentalblood-1.1.dist-info/METADATA
lsc_mentalblood-1.1.dist-info/WHEEL
lsc_mentalblood-1.1.dist-info/top_level.txt
lsc_mentalblood-1.1.dist-info/RECORD
