Metadata-Version: 2.1
Name: lsc-mentalblood
Version: 1.1
Summary: Compile wires "from, to" list to working C code
Home-page: https://github.com/MentalBlood/logic_schemes_compiler
Author: mentalblood
Author-email: neceporenkostepan@gmail.com
License: UNKNOWN
Project-URL: Bug Tracker, https://github.com/MentalBlood/logic_schemes_compiler/issues
Platform: UNKNOWN
Classifier: Programming Language :: Python :: 3
Classifier: License :: OSI Approved :: MIT License
Classifier: Operating System :: OS Independent
Requires-Python: >=3.7
License-File: LICENSE
